virus_total_apis/__init__.py
virus_total_apis/api.py
virustotal_api-1.1.10.dist-info/DESCRIPTION.rst
virustotal_api-1.1.10.dist-info/METADATA
virustotal_api-1.1.10.dist-info/RECORD
virustotal_api-1.1.10.dist-info/WHEEL
virustotal_api-1.1.10.dist-info/metadata.json
virustotal_api-1.1.10.dist-info/top_level.txt
