Metadata-Version: 2.0
Name: virustotal-api
Version: 1.1.10
Summary: Virus Total Public/Private/Intel API
Home-page: https://github.com/blacktop/virustotal-api
Author: blacktop
Author-email: dev@blacktop.io
License: MIT
Platform: UNKNOWN
Classifier: Development Status :: 5 - Production/Stable
Classifier: Intended Audience :: Developers
Classifier: Natural Language :: English
Classifier: License :: OSI Approved :: MIT License
Classifier: Programming Language :: Python :: 2.7
Classifier: Programming Language :: Python :: 3.5
Requires-Dist: requests (>=2.2.1)
